khonshu/__init__.py
khonshu/khonshu.py
khonshu/asyncscapy/__init__.py
khonshu/asyncscapy/aioarp.py
khonshu/asyncscapy/aioicmp.py
khonshu/asyncscapy/aiotcp.py
khonshu/asyncscapy/connectscan.py
khonshu/asyncscapy/synscan.py
khonshu/cidr/__init__.py
khonshu/cidr/cidr.py
khonshu/cli/__init__.py
khonshu/cli/cli.py
khonshu/diskmanager/__init__.py
khonshu/diskmanager/diskmanager.py
khonshu/interface/__init__.py
khonshu/interface/interfaces.py
khonshu/model/__init__.py
khonshu/model/alive.py
khonshu/model/interface.py
khonshu/model/request.py
khonshu/model/response.py
khonshu/passive/__init__.py
khonshu/passive/passive.py
khonshu/progresslogger/__init__.py
khonshu/progresslogger/progresslogger.py
khonshu/pyrunner/__init__.py
khonshu/pyrunner/pyrunner.py
khonshu/settings/__init__.py
khonshu/settings/settings.py
khonshu/utils/__init__.py
khonshu/utils/utils.py
khonshu-1.1.0.dist-info/METADATA
khonshu-1.1.0.dist-info/WHEEL
khonshu-1.1.0.dist-info/entry_points.txt
khonshu-1.1.0.dist-info/licenses/LICENSE
khonshu-1.1.0.dist-info/RECORD
