Metadata-Version: 2.4
Name: khonshu
Version: 1.1.0
Summary: Khonshu – A stealthy, concurrent port scanner written in asynchronous python that crafted for speed and accuracy.
Author-email: "D. Sanjai Kumar" <bughunterz0047@gmail.com>, "Gokul.V" <th3gokul@gmail.com>, Pugalarasan K <0xpugal@gmail.com>
Maintainer-email: "D. Sanjai Kumar" <bughunterz0047@gmail.com>, "Gokul.V" <th3gokul@gmail.com>, Pugalarasan K <0xpugal@gmail.com>
License-File: LICENSE
Requires-Python: >=3.13
Requires-Dist: aiolimiter>=1.2.1
Requires-Dist: aioping>=0.4.0
Requires-Dist: asyncio>=4.0.0
Requires-Dist: gitupdater>=1.0.0
Requires-Dist: revoltlogger>=1.0.1
Requires-Dist: revoltutils
Requires-Dist: richparser>=1.0.0
Requires-Dist: scapy>=2.6.1
Requires-Dist: shodanx==1.1.1
Requires-Dist: uvloop>=0.21.0
Requires-Dist: winloop>=0.1.91; sys_platform == 'win32'
